neutronics_pd/__init__.py
neutronics_pd/d1s_routines.py
neutronics_pd/fispact_tools.py
neutronics_pd/mcnp_output_tools.py
neutronics_pd/mctal_reader.py
neutronics_pd/meshtal_reader.py
neutronics_pd/meshtal_reader_bak.py
neutronics_pd/meshtal_reader_dev.py
neutronics_pd/pactiter_reader.py
neutronics_pd-0.1.5.dist-info/WHEEL
neutronics_pd-0.1.5.dist-info/METADATA
neutronics_pd-0.1.5.dist-info/RECORD
