Metadata-Version: 2.1
Name: neutronics-pd
Version: 0.1.5
Summary: Python Library for neutronics output
Home-page: https://gitlab.com/enea-fusion-neutronics/neutronics-pd
Author: gmariano
Author-email: giovanni.mariano@enea.it
Requires-Python: >=3.7
Classifier: Programming Language :: Python :: 3
Classifier: Programming Language :: Python :: 3.10
Classifier: Programming Language :: Python :: 3.7
Classifier: Programming Language :: Python :: 3.8
Classifier: Programming Language :: Python :: 3.9
Requires-Dist: datetime (>=4.3)
Requires-Dist: numpy (>=1.18.1)
Requires-Dist: openpyxl (==3.0.9)
Requires-Dist: pandas (>=1.0.1)
Requires-Dist: pathlib (>=1.0.1)
Requires-Dist: xarray (>=0.15.0)
Project-URL: Repository, https://gitlab.com/enea-fusion-neutronics/neutronics-pd
